github_copilot/__init__.py
github_copilot/main.py
github_copilot-0.3.0.dist-info/WHEEL
github_copilot-0.3.0.dist-info/METADATA
github_copilot-0.3.0.dist-info/RECORD
